Metadata-Version: 2.1
Name: odoo-rest-framework
Version: 1.1.9
Summary: Store user access token for one-time-login
Home-page: https://github.com/HanZawNyein/odoo-rest-framework.git
Author: Han Zaw Nyein
Author-email: hanzawnyineonline@gmail.com
